ml4ir/applications/classification/__init__.py
ml4ir/applications/classification/pipeline.py
ml4ir/applications/classification/config/__init__.py
ml4ir/applications/classification/config/keys.py
ml4ir/applications/classification/config/parse_args.py
ml4ir/applications/classification/model/__init__.py
ml4ir/applications/classification/model/classification_model.py
ml4ir/applications/classification/model/losses/__init__.py
ml4ir/applications/classification/model/losses/categorical_cross_entropy.py
ml4ir/applications/classification/model/metrics/__init__.py
ml4ir/applications/classification/model/metrics/metrics_factory.py
ml4ir/applications/classification/model/metrics/metrics_impl.py
ml4ir/applications/classification/tests/__init__.py
ml4ir/applications/classification/tests/generate_test_data.py
ml4ir/applications/classification/tests/test_base.py
ml4ir/applications/classification/tests/test_calibration.py
ml4ir/applications/classification/tests/test_classification_model.py
ml4ir/applications/classification/tests/test_classification_serving.py
ml4ir/applications/classification/tests/test_metrics.py
ml4ir/applications/classification/tests/test_tfrecord_reader.py
ml4ir/applications/classification/tests/data/configs/feature_config.yaml
ml4ir/applications/classification/tests/data/configs/model_config.yaml
ml4ir/applications/classification/tests/data/configs/vocabulary/domain_id.csv
ml4ir/applications/classification/tests/data/configs/vocabulary/entity_id.csv
ml4ir/applications/classification/tests/data/configs/vocabulary/query_word.csv
ml4ir/applications/classification/tests/data/csv/test/file_0.csv
ml4ir/applications/classification/tests/data/csv/train/file_0.csv
ml4ir/applications/classification/tests/data/csv/validation/file_0.csv
ml4ir/applications/classification/tests/data/tfrecord/test/file_0.tfrecord
ml4ir/applications/classification/tests/data/tfrecord/train/file_0.tfrecord
ml4ir/applications/classification/tests/data/tfrecord/validation/file_0.tfrecord
ml4ir-0.1.16.dist-info/LICENSE.txt
ml4ir-0.1.16.dist-info/METADATA
ml4ir-0.1.16.dist-info/WHEEL
ml4ir-0.1.16.dist-info/top_level.txt
ml4ir-0.1.16.dist-info/RECORD
