Metadata-Version: 2.1
Name: ml4ir
Version: 0.1.16
Summary: Machine Learning libraries for Information Retrieval
Home-page: https://www.salesforce.com/
Author: Search Relevance, Salesforce
Author-email: searchrelevancyscrumteam@salesforce.com
License: ASL 2.0
Platform: UNKNOWN
Classifier: License :: OSI Approved :: Apache Software License
Classifier: Programming Language :: Python :: 3 :: Only
Requires-Python: >=3.9
License-File: LICENSE.txt
Requires-Dist: tensorflow (==2.9.3)
Requires-Dist: numpy (==1.24.2)
Requires-Dist: pandas (==1.5.3)
Requires-Dist: scipy (==1.10.0)
Requires-Dist: PyYAML (==5.4.1)
Requires-Dist: opencv-python-headless (==4.6.0.66)
Requires-Dist: tf-models-official (==2.9.2)
Requires-Dist: tensorflow-probability (==0.15.0)
Provides-Extra: all
Requires-Dist: pyspark (==3.3.2) ; extra == 'all'
Requires-Dist: omnixai (==1.1.4) ; extra == 'all'
Requires-Dist: pygraphviz (==1.10) ; extra == 'all'
Provides-Extra: explainer
Requires-Dist: omnixai (==1.1.4) ; extra == 'explainer'
Provides-Extra: pyspark
Requires-Dist: pyspark (==3.0.1) ; extra == 'pyspark'
Provides-Extra: visualization
Requires-Dist: pygraphviz (==1.7) ; extra == 'visualization'
